{
  "text": "короче, я знаю, что сделать, у меня есть просто, я читаю New York Times, там научные исследования, лучшие специалисты по теме питания, я просто все эти платные статьи заберу, которые читаю, там мета-анализы, которые расписаны нормальным языком, я переведу их на польский, условно говоря, буду на основе этих... Ну да, переводить на...",
  "segments": [
    {
      "start": 0.0,
      "end": 26.26,
      "text": " короче, я знаю, что сделать, у меня есть просто, я читаю New York Times, там научные исследования, лучшие специалисты по теме питания, я просто все эти платные статьи заберу, которые читаю, там мета-анализы, которые расписаны нормальным языком, я переведу их на польский, условно говоря, буду на основе этих...",
      "words": [
        {
          "start": 0.0,
          "end": 0.16,
          "word": " короче,"
        },
        {
          "start": 0.22,
          "end": 0.36,
          "word": " я"
        },
        {
          "start": 0.36,
          "end": 0.68,
          "word": " знаю,"
        },
        {
          "start": 0.72,
          "end": 0.88,
          "word": " что"
        },
        {
          "start": 0.88,
          "end": 1.18,
          "word": " сделать,"
        },
        {
          "start": 1.42,
          "end": 1.92,
          "word": " у"
        },
        {
          "start": 1.92,
          "end": 2.12,
          "word": " меня"
        },
        {
          "start": 2.12,
          "end": 2.38,
          "word": " есть"
        },
        {
          "start": 2.38,
          "end": 2.68,
          "word": " просто,"
        },
        {
          "start": 2.72,
          "end": 2.92,
          "word": " я"
        },
        {
          "start": 2.92,
          "end": 3.36,
          "word": " читаю"
        },
        {
          "start": 3.36,
          "end": 3.56,
          "word": " New"
        },
        {
          "start": 3.56,
          "end": 3.78,
          "word": " York"
        },
        {
          "start": 3.78,
          "end": 4.08,
          "word": " Times,"
        },
        {
          "start": 4.36,
          "end": 5.22,
          "word": " там"
        },
        {
          "start": 5.22,
          "end": 5.78,
          "word": " научные"
        },
        {
          "start": 5.78,
          "end": 6.44,
          "word": " исследования,"
        },
        {
          "start": 6.52,
          "end": 6.94,
          "word": " лучшие"
        },
        {
          "start": 6.94,
          "end": 7.92,
          "word": " специалисты"
        },
        {
          "start": 7.92,
          "end": 8.1,
          "word": " по"
        },
        {
          "start": 8.1,
          "end": 8.64,
          "word": " теме"
        },
        {
          "start": 8.64,
          "end": 9.2,
          "word": " питания,"
        },
        {
          "start": 9.38,
          "end": 9.96,
          "word": " я"
        },
        {
          "start": 9.96,
          "end": 10.28,
          "word": " просто"
        },
        {
          "start": 10.28,
          "end": 10.72,
          "word": " все"
        },
        {
          "start": 10.72,
          "end": 11.06,
          "word": " эти"
        },
        {
          "start": 11.06,
          "end": 11.92,
          "word": " платные"
        },
        {
          "start": 11.92,
          "end": 12.34,
          "word": " статьи"
        },
        {
          "start": 12.34,
          "end": 12.78,
          "word": " заберу,"
        },
        {
          "start": 12.82,
          "end": 14.68,
          "word": " которые"
        },
        {
          "start": 14.68,
          "end": 15.44,
          "word": " читаю,"
        },
        {
          "start": 15.46,
          "end": 15.66,
          "word": " там"
        },
        {
          "start": 15.66,
          "end": 16.2,
          "word": " мета"
        },
        {
          "start": 16.2,
          "end": 16.76,
          "word": "-анализы,"
        },
        {
          "start": 16.78,
          "end": 17.02,
          "word": " которые"
        },
        {
          "start": 17.02,
          "end": 18.46,
          "word": " расписаны"
        },
        {
          "start": 18.46,
          "end": 19.0,
          "word": " нормальным"
        },
        {
          "start": 19.0,
          "end": 19.6,
          "word": " языком,"
        },
        {
          "start": 19.76,
          "end": 21.04,
          "word": " я"
        },
        {
          "start": 21.04,
          "end": 21.66,
          "word": " переведу"
        },
        {
          "start": 21.66,
          "end": 21.84,
          "word": " их"
        },
        {
          "start": 21.84,
          "end": 22.14,
          "word": " на"
        },
        {
          "start": 22.14,
          "end": 23.26,
          "word": " польский,"
        },
        {
          "start": 23.28,
          "end": 23.68,
          "word": " условно"
        },
        {
          "start": 23.68,
          "end": 23.96,
          "word": " говоря,"
        },
        {
          "start": 24.08,
          "end": 24.7,
          "word": " буду"
        },
        {
          "start": 24.7,
          "end": 25.16,
          "word": " на"
        },
        {
          "start": 25.16,
          "end": 25.66,
          "word": " основе"
        },
        {
          "start": 25.66,
          "end": 26.26,
          "word": " этих..."
        }
      ]
    },
    {
      "start": 30.0,
      "end": 30.94,
      "text": " Ну да, переводить на...",
      "words": [
        {
          "start": 30.0,
          "end": 30.1,
          "word": " Ну"
        },
        {
          "start": 30.1,
          "end": 30.22,
          "word": " да,"
        },
        {
          "start": 30.28,
          "end": 30.76,
          "word": " переводить"
        },
        {
          "start": 30.76,
          "end": 30.94,
          "word": " на..."
        }
      ]
    }
  ],
  "speaker": "track_1"
}