{
  "text": "Ну, я просто сделала такого бота в Labable, который говорит там, привет-привет, какие у тебя цели там по здоровью, по питанию, хочешь ли ты там похудеть или больше энергии, он отвечает на вопросы, и потом он выдает 4 опции корзины, в Labable это уже есть, типа, купи 4 корзины там, одна, например, овощи, фрукты, вторая мясо, рыба, третья молочные продукты, третья семена, например, эхи, масло, вот такое вот. И дальше я хочу вручную это как-то проверять и сама вручную им доставлять эти корзины. Я хочу привязать, сделать не просто ассистента, потому что даже по интервью я вижу, что в этом нет смысла, те, кому надо было, они создали проект целый в чате GPT и консультируются по питанию напрямую у чата GPT.",
  "segments": [
    {
      "start": 0.0,
      "end": 29.98,
      "text": " Ну, я просто сделала такого бота в Labable, который говорит там, привет-привет, какие у тебя цели там по здоровью, по питанию, хочешь ли ты там похудеть или больше энергии, он отвечает на вопросы, и потом он выдает 4 опции корзины, в Labable это уже есть, типа, купи 4 корзины там, одна, например, овощи, фрукты, вторая мясо, рыба, третья молочные продукты, третья семена, например, эхи, масло, вот такое вот.",
      "words": [
        {
          "start": 0.0,
          "end": 0.34,
          "word": " Ну,"
        },
        {
          "start": 0.36,
          "end": 0.66,
          "word": " я"
        },
        {
          "start": 0.66,
          "end": 1.08,
          "word": " просто"
        },
        {
          "start": 1.08,
          "end": 1.98,
          "word": " сделала"
        },
        {
          "start": 1.98,
          "end": 2.2,
          "word": " такого"
        },
        {
          "start": 2.2,
          "end": 2.68,
          "word": " бота"
        },
        {
          "start": 2.68,
          "end": 2.86,
          "word": " в"
        },
        {
          "start": 2.86,
          "end": 3.3,
          "word": " Labable,"
        },
        {
          "start": 3.44,
          "end": 3.76,
          "word": " который"
        },
        {
          "start": 3.76,
          "end": 4.22,
          "word": " говорит"
        },
        {
          "start": 4.22,
          "end": 4.58,
          "word": " там,"
        },
        {
          "start": 4.62,
          "end": 5.22,
          "word": " привет"
        },
        {
          "start": 5.22,
          "end": 5.58,
          "word": "-привет,"
        },
        {
          "start": 5.66,
          "end": 5.98,
          "word": " какие"
        },
        {
          "start": 5.98,
          "end": 6.16,
          "word": " у"
        },
        {
          "start": 6.16,
          "end": 6.36,
          "word": " тебя"
        },
        {
          "start": 6.36,
          "end": 6.96,
          "word": " цели"
        },
        {
          "start": 6.96,
          "end": 7.18,
          "word": " там"
        },
        {
          "start": 7.18,
          "end": 7.36,
          "word": " по"
        },
        {
          "start": 7.36,
          "end": 7.9,
          "word": " здоровью,"
        },
        {
          "start": 7.9,
          "end": 8.02,
          "word": " по"
        },
        {
          "start": 8.02,
          "end": 8.62,
          "word": " питанию,"
        },
        {
          "start": 8.62,
          "end": 8.98,
          "word": " хочешь"
        },
        {
          "start": 8.98,
          "end": 9.22,
          "word": " ли"
        },
        {
          "start": 9.22,
          "end": 9.36,
          "word": " ты"
        },
        {
          "start": 9.36,
          "end": 9.56,
          "word": " там"
        },
        {
          "start": 9.56,
          "end": 10.22,
          "word": " похудеть"
        },
        {
          "start": 10.22,
          "end": 10.54,
          "word": " или"
        },
        {
          "start": 10.54,
          "end": 10.88,
          "word": " больше"
        },
        {
          "start": 10.88,
          "end": 11.64,
          "word": " энергии,"
        },
        {
          "start": 11.66,
          "end": 11.8,
          "word": " он"
        },
        {
          "start": 11.8,
          "end": 12.3,
          "word": " отвечает"
        },
        {
          "start": 12.3,
          "end": 12.44,
          "word": " на"
        },
        {
          "start": 12.44,
          "end": 12.76,
          "word": " вопросы,"
        },
        {
          "start": 12.98,
          "end": 14.22,
          "word": " и"
        },
        {
          "start": 14.22,
          "end": 14.76,
          "word": " потом"
        },
        {
          "start": 14.76,
          "end": 15.0,
          "word": " он"
        },
        {
          "start": 15.0,
          "end": 15.5,
          "word": " выдает"
        },
        {
          "start": 15.5,
          "end": 15.84,
          "word": " 4"
        },
        {
          "start": 15.84,
          "end": 16.62,
          "word": " опции"
        },
        {
          "start": 16.62,
          "end": 17.2,
          "word": " корзины,"
        },
        {
          "start": 17.24,
          "end": 17.32,
          "word": " в"
        },
        {
          "start": 17.32,
          "end": 17.62,
          "word": " Labable"
        },
        {
          "start": 17.62,
          "end": 17.9,
          "word": " это"
        },
        {
          "start": 17.9,
          "end": 18.12,
          "word": " уже"
        },
        {
          "start": 18.12,
          "end": 18.42,
          "word": " есть,"
        },
        {
          "start": 18.52,
          "end": 18.74,
          "word": " типа,"
        },
        {
          "start": 18.84,
          "end": 20.4,
          "word": " купи"
        },
        {
          "start": 20.4,
          "end": 20.86,
          "word": " 4"
        },
        {
          "start": 20.86,
          "end": 21.58,
          "word": " корзины"
        },
        {
          "start": 21.58,
          "end": 21.82,
          "word": " там,"
        },
        {
          "start": 21.9,
          "end": 22.26,
          "word": " одна,"
        },
        {
          "start": 22.34,
          "end": 22.6,
          "word": " например,"
        },
        {
          "start": 22.72,
          "end": 23.22,
          "word": " овощи,"
        },
        {
          "start": 23.24,
          "end": 23.7,
          "word": " фрукты,"
        },
        {
          "start": 23.74,
          "end": 24.06,
          "word": " вторая"
        },
        {
          "start": 24.06,
          "end": 24.44,
          "word": " мясо,"
        },
        {
          "start": 24.44,
          "end": 24.78,
          "word": " рыба,"
        },
        {
          "start": 24.8,
          "end": 25.24,
          "word": " третья"
        },
        {
          "start": 25.24,
          "end": 25.86,
          "word": " молочные"
        },
        {
          "start": 25.86,
          "end": 26.4,
          "word": " продукты,"
        },
        {
          "start": 26.46,
          "end": 27.06,
          "word": " третья"
        },
        {
          "start": 27.06,
          "end": 27.82,
          "word": " семена,"
        },
        {
          "start": 27.96,
          "end": 28.24,
          "word": " например,"
        },
        {
          "start": 28.4,
          "end": 28.94,
          "word": " эхи,"
        },
        {
          "start": 28.94,
          "end": 29.32,
          "word": " масло,"
        },
        {
          "start": 29.32,
          "end": 29.46,
          "word": " вот"
        },
        {
          "start": 29.46,
          "end": 29.74,
          "word": " такое"
        },
        {
          "start": 29.74,
          "end": 29.98,
          "word": " вот."
        }
      ]
    },
    {
      "start": 30.0,
      "end": 37.7,
      "text": " И дальше я хочу вручную это как-то проверять и сама вручную им доставлять эти корзины.",
      "words": [
        {
          "start": 30.0,
          "end": 30.7,
          "word": " И"
        },
        {
          "start": 30.7,
          "end": 31.28,
          "word": " дальше"
        },
        {
          "start": 31.28,
          "end": 31.58,
          "word": " я"
        },
        {
          "start": 31.58,
          "end": 31.82,
          "word": " хочу"
        },
        {
          "start": 31.82,
          "end": 32.86,
          "word": " вручную"
        },
        {
          "start": 32.86,
          "end": 33.12,
          "word": " это"
        },
        {
          "start": 33.12,
          "end": 33.38,
          "word": " как"
        },
        {
          "start": 33.38,
          "end": 33.64,
          "word": "-то"
        },
        {
          "start": 33.64,
          "end": 34.22,
          "word": " проверять"
        },
        {
          "start": 34.22,
          "end": 34.78,
          "word": " и"
        },
        {
          "start": 34.78,
          "end": 35.02,
          "word": " сама"
        },
        {
          "start": 35.02,
          "end": 35.76,
          "word": " вручную"
        },
        {
          "start": 35.76,
          "end": 36.02,
          "word": " им"
        },
        {
          "start": 36.02,
          "end": 37.08,
          "word": " доставлять"
        },
        {
          "start": 37.08,
          "end": 37.22,
          "word": " эти"
        },
        {
          "start": 37.22,
          "end": 37.7,
          "word": " корзины."
        }
      ]
    },
    {
      "start": 38.7,
      "end": 52.0,
      "text": " Я хочу привязать, сделать не просто ассистента, потому что даже по интервью я вижу, что в этом нет смысла, те, кому надо было, они создали проект целый в чате GPT и консультируются по питанию напрямую у чата GPT.",
      "words": [
        {
          "start": 38.7,
          "end": 39.22,
          "word": " Я"
        },
        {
          "start": 39.22,
          "end": 39.56,
          "word": " хочу"
        },
        {
          "start": 39.56,
          "end": 40.34,
          "word": " привязать,"
        },
        {
          "start": 40.34,
          "end": 40.5,
          "word": " сделать"
        },
        {
          "start": 40.5,
          "end": 40.74,
          "word": " не"
        },
        {
          "start": 40.74,
          "end": 40.98,
          "word": " просто"
        },
        {
          "start": 40.98,
          "end": 41.68,
          "word": " ассистента,"
        },
        {
          "start": 41.68,
          "end": 41.88,
          "word": " потому"
        },
        {
          "start": 41.88,
          "end": 42.08,
          "word": " что"
        },
        {
          "start": 42.08,
          "end": 42.3,
          "word": " даже"
        },
        {
          "start": 42.3,
          "end": 42.48,
          "word": " по"
        },
        {
          "start": 42.48,
          "end": 42.9,
          "word": " интервью"
        },
        {
          "start": 42.9,
          "end": 43.1,
          "word": " я"
        },
        {
          "start": 43.1,
          "end": 43.44,
          "word": " вижу,"
        },
        {
          "start": 43.48,
          "end": 43.68,
          "word": " что"
        },
        {
          "start": 43.68,
          "end": 43.74,
          "word": " в"
        },
        {
          "start": 43.74,
          "end": 43.92,
          "word": " этом"
        },
        {
          "start": 43.92,
          "end": 44.1,
          "word": " нет"
        },
        {
          "start": 44.1,
          "end": 44.64,
          "word": " смысла,"
        },
        {
          "start": 44.64,
          "end": 45.06,
          "word": " те,"
        },
        {
          "start": 45.14,
          "end": 45.38,
          "word": " кому"
        },
        {
          "start": 45.38,
          "end": 45.58,
          "word": " надо"
        },
        {
          "start": 45.58,
          "end": 45.86,
          "word": " было,"
        },
        {
          "start": 45.96,
          "end": 46.16,
          "word": " они"
        },
        {
          "start": 46.16,
          "end": 46.7,
          "word": " создали"
        },
        {
          "start": 46.7,
          "end": 47.28,
          "word": " проект"
        },
        {
          "start": 47.28,
          "end": 47.96,
          "word": " целый"
        },
        {
          "start": 47.96,
          "end": 48.04,
          "word": " в"
        },
        {
          "start": 48.04,
          "end": 48.82,
          "word": " чате"
        },
        {
          "start": 48.82,
          "end": 49.4,
          "word": " GPT"
        },
        {
          "start": 49.4,
          "end": 49.62,
          "word": " и"
        },
        {
          "start": 49.62,
          "end": 50.34,
          "word": " консультируются"
        },
        {
          "start": 50.34,
          "end": 50.52,
          "word": " по"
        },
        {
          "start": 50.52,
          "end": 51.0,
          "word": " питанию"
        },
        {
          "start": 51.0,
          "end": 51.6,
          "word": " напрямую"
        },
        {
          "start": 51.6,
          "end": 51.68,
          "word": " у"
        },
        {
          "start": 51.68,
          "end": 51.92,
          "word": " чата"
        },
        {
          "start": 51.92,
          "end": 52.0,
          "word": " GPT."
        }
      ]
    }
  ],
  "speaker": "track_1"
}