{
  "text": "вообще ничего не делать, не делать решения, просто взять чат ШПТ готовый с промтом",
  "segments": [
    {
      "start": 0.0,
      "end": 4.48,
      "text": " вообще ничего не делать, не делать решения, просто взять чат ШПТ готовый с промтом",
      "words": [
        {
          "start": 0.0,
          "end": 0.24,
          "word": " вообще"
        },
        {
          "start": 0.24,
          "end": 0.46,
          "word": " ничего"
        },
        {
          "start": 0.46,
          "end": 0.72,
          "word": " не"
        },
        {
          "start": 0.72,
          "end": 1.14,
          "word": " делать,"
        },
        {
          "start": 1.18,
          "end": 1.3,
          "word": " не"
        },
        {
          "start": 1.3,
          "end": 1.56,
          "word": " делать"
        },
        {
          "start": 1.56,
          "end": 2.1,
          "word": " решения,"
        },
        {
          "start": 2.1,
          "end": 2.36,
          "word": " просто"
        },
        {
          "start": 2.36,
          "end": 2.7,
          "word": " взять"
        },
        {
          "start": 2.7,
          "end": 3.06,
          "word": " чат"
        },
        {
          "start": 3.06,
          "end": 3.38,
          "word": " ШПТ"
        },
        {
          "start": 3.38,
          "end": 3.96,
          "word": " готовый"
        },
        {
          "start": 3.96,
          "end": 4.0,
          "word": " с"
        },
        {
          "start": 4.0,
          "end": 4.48,
          "word": " промтом"
        }
      ]
    }
  ],
  "speaker": "track_1"
}