{
  "text": "Ну вот смотрите, вы говорите, что вот за это тебя сложно любить. Но и подмечают, что смотрите, он тебя любит. Вот как важна любовь даже одного человека.",
  "segments": [
    {
      "start": 0.0,
      "end": 6.3,
      "text": " Ну вот смотрите, вы говорите, что вот за это тебя сложно любить.",
      "words": [
        {
          "start": 0.0,
          "end": 0.18,
          "word": " Ну"
        },
        {
          "start": 0.18,
          "end": 0.48,
          "word": " вот"
        },
        {
          "start": 0.48,
          "end": 1.12,
          "word": " смотрите,"
        },
        {
          "start": 1.4,
          "end": 1.52,
          "word": " вы"
        },
        {
          "start": 1.52,
          "end": 2.12,
          "word": " говорите,"
        },
        {
          "start": 2.14,
          "end": 3.22,
          "word": " что"
        },
        {
          "start": 3.22,
          "end": 3.64,
          "word": " вот"
        },
        {
          "start": 3.64,
          "end": 4.16,
          "word": " за"
        },
        {
          "start": 4.16,
          "end": 4.52,
          "word": " это"
        },
        {
          "start": 4.52,
          "end": 4.98,
          "word": " тебя"
        },
        {
          "start": 4.98,
          "end": 5.48,
          "word": " сложно"
        },
        {
          "start": 5.48,
          "end": 6.3,
          "word": " любить."
        }
      ]
    },
    {
      "start": 6.34,
      "end": 11.06,
      "text": " Но и подмечают, что смотрите, он тебя любит.",
      "words": [
        {
          "start": 6.34,
          "end": 6.9,
          "word": " Но"
        },
        {
          "start": 6.9,
          "end": 7.1,
          "word": " и"
        },
        {
          "start": 7.1,
          "end": 7.78,
          "word": " подмечают,"
        },
        {
          "start": 7.86,
          "end": 8.08,
          "word": " что"
        },
        {
          "start": 8.08,
          "end": 9.32,
          "word": " смотрите,"
        },
        {
          "start": 9.46,
          "end": 9.76,
          "word": " он"
        },
        {
          "start": 9.76,
          "end": 10.04,
          "word": " тебя"
        },
        {
          "start": 10.04,
          "end": 11.06,
          "word": " любит."
        }
      ]
    },
    {
      "start": 11.06,
      "end": 14.12,
      "text": " Вот как важна любовь даже одного человека.",
      "words": [
        {
          "start": 11.06,
          "end": 11.24,
          "word": " Вот"
        },
        {
          "start": 11.24,
          "end": 11.46,
          "word": " как"
        },
        {
          "start": 11.46,
          "end": 12.06,
          "word": " важна"
        },
        {
          "start": 12.06,
          "end": 13.38,
          "word": " любовь"
        },
        {
          "start": 13.38,
          "end": 13.5,
          "word": " даже"
        },
        {
          "start": 13.5,
          "end": 13.98,
          "word": " одного"
        },
        {
          "start": 13.98,
          "end": 14.12,
          "word": " человека."
        }
      ]
    }
  ],
  "speaker": "track_1"
}