{
  "text": "Я там Михаилу на неделе скидываю.",
  "segments": [
    {
      "start": 0.0,
      "end": 1.92,
      "text": " Я там Михаилу на неделе скидываю.",
      "words": [
        {
          "start": 0.0,
          "end": 0.18,
          "word": " Я"
        },
        {
          "start": 0.18,
          "end": 0.26,
          "word": " там"
        },
        {
          "start": 0.26,
          "end": 1.0,
          "word": " Михаилу"
        },
        {
          "start": 1.0,
          "end": 1.16,
          "word": " на"
        },
        {
          "start": 1.16,
          "end": 1.62,
          "word": " неделе"
        },
        {
          "start": 1.62,
          "end": 1.92,
          "word": " скидываю."
        }
      ]
    }
  ],
  "speaker": "track_1"
}