{
  "text": "Так, фразу про публикацию. Для того, чтобы выложить на архив, мне нужно, чтобы аккаунт был апрулен. Соответственно, нужен какой-то рецензент, который за тебя...",
  "segments": [
    {
      "start": 0.94,
      "end": 4.22,
      "text": " Так, фразу про публикацию.",
      "words": [
        {
          "start": 0.94,
          "end": 1.98,
          "word": " Так,"
        },
        {
          "start": 2.26,
          "end": 3.04,
          "word": " фразу"
        },
        {
          "start": 3.04,
          "end": 3.44,
          "word": " про"
        },
        {
          "start": 3.44,
          "end": 4.22,
          "word": " публикацию."
        }
      ]
    },
    {
      "start": 4.58,
      "end": 8.28,
      "text": " Для того, чтобы выложить на архив, мне нужно, чтобы аккаунт был апрулен.",
      "words": [
        {
          "start": 4.58,
          "end": 5.14,
          "word": " Для"
        },
        {
          "start": 5.14,
          "end": 5.32,
          "word": " того,"
        },
        {
          "start": 5.36,
          "end": 5.48,
          "word": " чтобы"
        },
        {
          "start": 5.48,
          "end": 5.84,
          "word": " выложить"
        },
        {
          "start": 5.84,
          "end": 5.94,
          "word": " на"
        },
        {
          "start": 5.94,
          "end": 6.28,
          "word": " архив,"
        },
        {
          "start": 6.28,
          "end": 6.64,
          "word": " мне"
        },
        {
          "start": 6.64,
          "end": 6.96,
          "word": " нужно,"
        },
        {
          "start": 6.98,
          "end": 7.16,
          "word": " чтобы"
        },
        {
          "start": 7.16,
          "end": 7.58,
          "word": " аккаунт"
        },
        {
          "start": 7.58,
          "end": 7.74,
          "word": " был"
        },
        {
          "start": 7.74,
          "end": 8.28,
          "word": " апрулен."
        }
      ]
    },
    {
      "start": 9.3,
      "end": 11.72,
      "text": " Соответственно, нужен какой-то рецензент, который за тебя...",
      "words": [
        {
          "start": 9.3,
          "end": 9.86,
          "word": " Соответственно,"
        },
        {
          "start": 9.86,
          "end": 10.04,
          "word": " нужен"
        },
        {
          "start": 10.04,
          "end": 10.32,
          "word": " какой"
        },
        {
          "start": 10.32,
          "end": 10.5,
          "word": "-то"
        },
        {
          "start": 10.5,
          "end": 11.0,
          "word": " рецензент,"
        },
        {
          "start": 11.0,
          "end": 11.26,
          "word": " который"
        },
        {
          "start": 11.26,
          "end": 11.44,
          "word": " за"
        },
        {
          "start": 11.44,
          "end": 11.72,
          "word": " тебя..."
        }
      ]
    }
  ],
  "speaker": "track_1"
}